blitzactions/__init__.py
blitzactions/exceptions.py
blitzactions/manager.py
blitzactions/models.py
blitzactions-0.0.1.dist-info/METADATA
blitzactions-0.0.1.dist-info/WHEEL
blitzactions-0.0.1.dist-info/top_level.txt
blitzactions-0.0.1.dist-info/RECORD
