Metadata-Version: 2.1
Name: blitzactions
Version: 0.0.1
Summary: A package to test openai
Home-page: https://github.com/BlitzJB/blitzactions
Author: Rudra
Author-email: blitz04.dev@gmailc.com
Classifier: Programming Language :: Python :: 3
Classifier: License :: OSI Approved :: MIT License
Classifier: Operating System :: OS Independent
Requires-Python: >=3.6
Requires-Dist: openai
Requires-Dist: python-dotenv
